question_framework/__init__.py
question_framework/post_process/__init__.py
question_framework/post_process/post_process.py
question_framework/question/__init__.py
question_framework/question/question.py
question_framework/user_input/__init__.py
question_framework/user_input/user_input.py
question_framework/validation/__init__.py
question_framework/validation/validation.py
question_framework-0.2.0.dist-info/LICENSE
question_framework-0.2.0.dist-info/METADATA
question_framework-0.2.0.dist-info/WHEEL
question_framework-0.2.0.dist-info/top_level.txt
question_framework-0.2.0.dist-info/RECORD
