Metadata-Version: 2.1
Name: question-framework
Version: 0.2.0
Summary: Framework for asking questions
Home-page: https://github.com/dapryor/question-framework
Author: David Pryor
Author-email: dapryor@cisco.com
License: MIT
Platform: UNKNOWN
Classifier: Programming Language :: Python :: 3
Classifier: Operating System :: OS Independent
Requires-Python: >=3.6
